intercept/__init__.py
intercept/intercept.py
intercept-0.1.2.dist-info/DESCRIPTION.rst
intercept-0.1.2.dist-info/METADATA
intercept-0.1.2.dist-info/metadata.json
intercept-0.1.2.dist-info/RECORD
intercept-0.1.2.dist-info/top_level.txt
intercept-0.1.2.dist-info/WHEEL
