Metadata-Version: 2.0
Name: intercept
Version: 0.1.2
Summary: Capture your exceptions with a decorator.
Home-page: https://github.com/ikanor/interceptor
Author: Franky Rodriguez
Author-email: prados@gmail.com
License: MIT
Platform: UNKNOWN
Classifier: Development Status :: 3 - Alpha
Classifier: Intended Audience :: Developers
Classifier: Topic :: Software Development :: Libraries
Classifier: License :: OSI Approved :: MIT License
Classifier: Programming Language :: Python :: 3.5
